{
  "generated_at": "2026-03-19T12:46:27.348315+00:00",
  "prices": {
    "brent": {
      "name": "Brent Oil",
      "price": 106.59,
      "change": -0.74,
      "formatted_price": "$106.59",
      "formatted_change": "-0.74%",
      "updated_at": "2026-03-19T12:46:26.722050+00:00"
    },
    "gas": {
      "name": "Natural Gas",
      "price": 3.187,
      "change": 3.98,
      "formatted_price": "$3.187",
      "formatted_change": "+3.98%",
      "updated_at": "2026-03-19T12:46:26.840868+00:00"
    },
    "gold": {
      "name": "Gold",
      "price": 4613.1,
      "change": -5.66,
      "formatted_price": "$4613",
      "formatted_change": "-5.66%",
      "updated_at": "2026-03-19T12:46:26.962543+00:00"
    },
    "bitcoin": {
      "name": "Bitcoin",
      "price": 69661.39,
      "change": -2.22,
      "formatted_price": "$69,661",
      "formatted_change": "-2.22%",
      "updated_at": "2026-03-19T12:46:27.084916+00:00"
    },
    "iron": {
      "name": "Iron Ore",
      "price": 59.135,
      "change": -2.88,
      "formatted_price": "$59.13",
      "formatted_change": "-2.88%",
      "updated_at": "2026-03-19T12:46:27.202200+00:00"
    },
    "copper": {
      "name": "Copper",
      "price": 5.382,
      "change": -3.1,
      "formatted_price": "$5.38",
      "formatted_change": "-3.10%",
      "updated_at": "2026-03-19T12:46:27.348294+00:00"
    }
  }
}